Telethon_aio-1.0.dist-info/METADATA
Telethon_aio-1.0.dist-info/RECORD
Telethon_aio-1.0.dist-info/WHEEL
Telethon_aio-1.0.dist-info/top_level.txt
telethon/__init__.py
telethon/helpers.py
telethon/updatestate.py
telethon/utils.py
telethon/version.py
telethon/client/__init__.py
telethon/client/auth.py
telethon/client/chats.py
telethon/client/dialogs.py
telethon/client/downloads.py
telethon/client/messageparse.py
telethon/client/messages.py
telethon/client/telegrambaseclient.py
telethon/client/telegramclient.py
telethon/client/updates.py
telethon/client/uploads.py
telethon/client/users.py
telethon/crypto/__init__.py
telethon/crypto/aes.py
telethon/crypto/aesctr.py
telethon/crypto/authkey.py
telethon/crypto/cdndecrypter.py
telethon/crypto/factorization.py
telethon/crypto/rsa.py
telethon/errors/__init__.py
telethon/errors/common.py
telethon/errors/rpcbaseerrors.py
telethon/errors/rpcerrorlist.py
telethon/events/__init__.py
telethon/events/chataction.py
telethon/events/common.py
telethon/events/messagedeleted.py
telethon/events/messageedited.py
telethon/events/messageread.py
telethon/events/newmessage.py
telethon/events/raw.py
telethon/events/userupdate.py
telethon/extensions/__init__.py
telethon/extensions/binaryreader.py
telethon/extensions/html.py
telethon/extensions/markdown.py
telethon/extensions/tcpclient.py
telethon/network/__init__.py
telethon/network/authenticator.py
telethon/network/mtprotoplainsender.py
telethon/network/mtprotosender.py
telethon/network/mtprotostate.py
telethon/network/connection/__init__.py
telethon/network/connection/common.py
telethon/network/connection/tcpabridged.py
telethon/network/connection/tcpfull.py
telethon/network/connection/tcpintermediate.py
telethon/network/connection/tcpobfuscated.py
telethon/sessions/__init__.py
telethon/sessions/abstract.py
telethon/sessions/memory.py
telethon/sessions/sqlite.py
telethon/tl/__init__.py
telethon/tl/alltlobjects.py
telethon/tl/tlobject.py
telethon/tl/core/__init__.py
telethon/tl/core/gzippacked.py
telethon/tl/core/messagecontainer.py
telethon/tl/core/rpcresult.py
