Metadata-Version: 2.1
Name: Telethon-aio
Version: 1.0
Summary: Full-featured Telegram client library for Python 3
Home-page: https://github.com/LonamiWebs/Telethon
Author: Lonami Exo
Author-email: totufals@hotmail.com
License: MIT
Download-URL: https://github.com/LonamiWebs/Telethon/releases
Keywords: telegram api chat client library messaging mtproto
Platform: UNKNOWN
Classifier: Development Status :: 3 - Alpha
Classifier: Intended Audience :: Developers
Classifier: Topic :: Communications :: Chat
Classifier: License :: OSI Approved :: MIT License
Classifier: Programming Language :: Python :: 3
Classifier: Programming Language :: Python :: 3.5
Classifier: Programming Language :: Python :: 3.6
Requires-Python: >=3.5
Provides-Extra: cryptg
Requires-Dist: pyaes
Requires-Dist: rsa
Requires-Dist: async-generator
Provides-Extra: cryptg
Requires-Dist: cryptg; extra == 'cryptg'
